LICENSE.txt
README.md
setup.py
tzxlib/__init__.py
tzxlib/convert.py
tzxlib/loader.py
tzxlib/saver.py
tzxlib/tapfile.py
tzxlib/tzxblocks.py
tzxlib/tzxfile.py
tzxlib/z80dis.py
tzxtools/__init__.py
tzxtools/tzxcat.py
tzxtools/tzxcleanup.py
tzxtools/tzxcut.py
tzxtools/tzxls.py
tzxtools/tzxmerge.py
tzxtools/tzxplay.py
tzxtools/tzxsplit.py
tzxtools/tzxtap.py
tzxtools/tzxwav.py
tzxtools.egg-info/PKG-INFO
tzxtools.egg-info/SOURCES.txt
tzxtools.egg-info/dependency_links.txt
tzxtools.egg-info/entry_points.txt
tzxtools.egg-info/requires.txt
tzxtools.egg-info/top_level.txt