Metadata-Version: 2.1
Name: tzxtools
Version: 1.9.3
Summary: A tool collection for processing tzx files
Home-page: https://codeberg.org/shred/tzxtools
Author: Richard Körber
Author-email: dev@shredzone.de
License: GPLv3+
Project-URL: Source, https://codeberg.org/shred/tzxtools
Project-URL: Tracker, https://codeberg.org/shred/tzxtools/issues
Keywords: ZX-Spectrum tzx wav
Classifier: Development Status :: 5 - Production/Stable
Classifier: Environment :: Console
Classifier: Intended Audience :: Developers
Classifier: Intended Audience :: End Users/Desktop
Classifier: License :: OSI Approved :: GNU General Public License v3 or later (GPLv3+)
Classifier: Operating System :: OS Independent
Classifier: Programming Language :: Python :: 3 :: Only
Classifier: Topic :: System :: Archiving
Classifier: Topic :: System :: Emulators
Classifier: Topic :: Utilities
Requires-Python: >=3
License-File: LICENSE.txt
Requires-Dist: numpy>=1.20.0
Requires-Dist: pypng>=0.0.20
Requires-Dist: sounddevice>=0.4.0
